{"pickable_object_name": "apo-ferritin", "user_id": "curation", "session_id": "0", "run_name": "TS_99_9", "voxel_spacing": null, "unit": "angstrom", "points": [{"location": {"x": 6072.464, "y": 4038.0, "z": 715.679}, "transformation_": [[1.0, 0.0, 0.0, 0.0], [0.0, 1.0, 0.0, 0.0], [0.0, 0.0, 1.0, 0.0], [0.0, 0.0, 0.0, 1.0]], "instance_id": 0}, {"location": {"x": 5967.452, "y": 4228.213, "z": 1124.601}, "transformation_": [[1.0, 0.0, 0.0, 0.0], [0.0, 1.0, 0.0, 0.0], [0.0, 0.0, 1.0, 0.0], [0.0, 0.0, 0.0, 1.0]], "instance_id": 0}, {"location": {"x": 5847.622, "y": 5066.71, "z": 678.893}, "transformation_": [[1.0, 0.0, 0.0, 0.0], [0.0, 1.0, 0.0, 0.0], [0.0, 0.0, 1.0, 0.0], [0.0, 0.0, 0.0, 1.0]], "instance_id": 0}, {"location": {"x": 472.853, "y": 5632.618, "z": 580.676}, "transformation_": [[1.0, 0.0, 0.0, 0.0], [0.0, 1.0, 0.0, 0.0], [0.0, 0.0, 1.0, 0.0], [0.0, 0.0, 0.0, 1.0]], "instance_id": 0}, {"location": {"x": 564.507, "y": 5604.88, "z": 678.16}, "transformation_": [[1.0, 0.0, 0.0, 0.0], [0.0, 1.0, 0.0, 0.0], [0.0, 0.0, 1.0, 0.0], [0.0, 0.0, 0.0, 1.0]], "instance_id": 0}, {"location": {"x": 890.414, "y": 5615.759, "z": 467.69}, "transformation_": [[1.0, 0.0, 0.0, 0.0], [0.0, 1.0, 0.0, 0.0], [0.0, 0.0, 1.0, 0.0], [0.0, 0.0, 0.0, 1.0]], "instance_id": 0}, {"location": {"x": 5613.561, "y": 672.73, "z": 265.579}, "transformation_": [[1.0, 0.0, 0.0, 0.0], [0.0, 1.0, 0.0, 0.0], [0.0, 0.0, 1.0, 0.0], [0.0, 0.0, 0.0, 1.0]], "instance_id": 0}, {"location": {"x": 458.087, "y": 1972.013, "z": 765.906}, "transformation_": [[1.0, 0.0, 0.0, 0.0], [0.0, 1.0, 0.0, 0.0], [0.0, 0.0, 1.0, 0.0], [0.0, 0.0, 0.0, 1.0]], "instance_id": 0}, {"location": {"x": 1284.111, "y": 1752.411, "z": 250.87}, "transformation_": [[1.0, 0.0, 0.0, 0.0], [0.0, 1.0, 0.0, 0.0], [0.0, 0.0, 1.0, 0.0], [0.0, 0.0, 0.0, 1.0]], "instance_id": 0}, {"location": {"x": 1284.136, "y": 1713.797, "z": 367.525}, "transformation_": [[1.0, 0.0, 0.0, 0.0], [0.0, 1.0, 0.0, 0.0], [0.0, 0.0, 1.0, 0.0], [0.0, 0.0, 0.0, 1.0]], "instance_id": 0}, {"location": {"x": 1233.112, "y": 2053.458, "z": 251.902}, "transformation_": [[1.0, 0.0, 0.0, 0.0], [0.0, 1.0, 0.0, 0.0], [0.0, 0.0, 1.0, 0.0], [0.0, 0.0, 0.0, 1.0]], "instance_id": 0}, {"location": {"x": 1194.107, "y": 1911.285, "z": 267.179}, "transformation_": [[1.0, 0.0, 0.0, 0.0], [0.0, 1.0, 0.0, 0.0], [0.0, 0.0, 1.0, 0.0], [0.0, 0.0, 0.0, 1.0]], "instance_id": 0}, {"location": {"x": 5543.161, "y": 2879.598, "z": 408.42}, "transformation_": [[1.0, 0.0, 0.0, 0.0], [0.0, 1.0, 0.0, 0.0], [0.0, 0.0, 1.0, 0.0], [0.0, 0.0, 0.0, 1.0]], "instance_id": 0}, {"location": {"x": 5485.217, "y": 2774.62, "z": 411.413}, "transformation_": [[1.0, 0.0, 0.0, 0.0], [0.0, 1.0, 0.0, 0.0], [0.0, 0.0, 1.0, 0.0], [0.0, 0.0, 0.0, 1.0]], "instance_id": 0}, {"location": {"x": 5448.11, "y": 3486.46, "z": 985.533}, "transformation_": [[1.0, 0.0, 0.0, 0.0], [0.0, 1.0, 0.0, 0.0], [0.0, 0.0, 1.0, 0.0], [0.0, 0.0, 0.0, 1.0]], "instance_id": 0}, {"location": {"x": 3529.611, "y": 2919.728, "z": 380.389}, "transformation_": [[1.0, 0.0, 0.0, 0.0], [0.0, 1.0, 0.0, 0.0], [0.0, 0.0, 1.0, 0.0], [0.0, 0.0, 0.0, 1.0]], "instance_id": 0}, {"location": {"x": 3438.216, "y": 3010.29, "z": 397.925}, "transformation_": [[1.0, 0.0, 0.0, 0.0], [0.0, 1.0, 0.0, 0.0], [0.0, 0.0, 1.0, 0.0], [0.0, 0.0, 0.0, 1.0]], "instance_id": 0}, {"location": {"x": 4251.254, "y": 845.627, "z": 720.143}, "transformation_": [[1.0, 0.0, 0.0, 0.0], [0.0, 1.0, 0.0, 0.0], [0.0, 0.0, 1.0, 0.0], [0.0, 0.0, 0.0, 1.0]], "instance_id": 0}, {"location": {"x": 4592.044, "y": 1321.788, "z": 322.883}, "transformation_": [[1.0, 0.0, 0.0, 0.0], [0.0, 1.0, 0.0, 0.0], [0.0, 0.0, 1.0, 0.0], [0.0, 0.0, 0.0, 1.0]], "instance_id": 0}, {"location": {"x": 4250.071, "y": 1837.26, "z": 319.929}, "transformation_": [[1.0, 0.0, 0.0, 0.0], [0.0, 1.0, 0.0, 0.0], [0.0, 0.0, 1.0, 0.0], [0.0, 0.0, 0.0, 1.0]], "instance_id": 0}, {"location": {"x": 4395.13, "y": 1892.857, "z": 352.013}, "transformation_": [[1.0, 0.0, 0.0, 0.0], [0.0, 1.0, 0.0, 0.0], [0.0, 0.0, 1.0, 0.0], [0.0, 0.0, 0.0, 1.0]], "instance_id": 0}, {"location": {"x": 3670.295, "y": 1851.882, "z": 328.745}, "transformation_": [[1.0, 0.0, 0.0, 0.0], [0.0, 1.0, 0.0, 0.0], [0.0, 0.0, 1.0, 0.0], [0.0, 0.0, 0.0, 1.0]], "instance_id": 0}, {"location": {"x": 3287.917, "y": 1286.28, "z": 282.56}, "transformation_": [[1.0, 0.0, 0.0, 0.0], [0.0, 1.0, 0.0, 0.0], [0.0, 0.0, 1.0, 0.0], [0.0, 0.0, 0.0, 1.0]], "instance_id": 0}, {"location": {"x": 2967.331, "y": 1646.264, "z": 312.781}, "transformation_": [[1.0, 0.0, 0.0, 0.0], [0.0, 1.0, 0.0, 0.0], [0.0, 0.0, 1.0, 0.0], [0.0, 0.0, 0.0, 1.0]], "instance_id": 0}, {"location": {"x": 2987.912, "y": 1729.794, "z": 397.471}, "transformation_": [[1.0, 0.0, 0.0, 0.0], [0.0, 1.0, 0.0, 0.0], [0.0, 0.0, 1.0, 0.0], [0.0, 0.0, 0.0, 1.0]], "instance_id": 0}, {"location": {"x": 652.0, "y": 4574.214, "z": 416.571}, "transformation_": [[1.0, 0.0, 0.0, 0.0], [0.0, 1.0, 0.0, 0.0], [0.0, 0.0, 1.0, 0.0], [0.0, 0.0, 0.0, 1.0]], "instance_id": 0}, {"location": {"x": 1032.835, "y": 4506.417, "z": 1003.228}, "transformation_": [[1.0, 0.0, 0.0, 0.0], [0.0, 1.0, 0.0, 0.0], [0.0, 0.0, 1.0, 0.0], [0.0, 0.0, 0.0, 1.0]], "instance_id": 0}, {"location": {"x": 1100.435, "y": 4449.249, "z": 1078.617}, "transformation_": [[1.0, 0.0, 0.0, 0.0], [0.0, 1.0, 0.0, 0.0], [0.0, 0.0, 1.0, 0.0], [0.0, 0.0, 0.0, 1.0]], "instance_id": 0}, {"location": {"x": 929.932, "y": 4524.384, "z": 915.137}, "transformation_": [[1.0, 0.0, 0.0, 0.0], [0.0, 1.0, 0.0, 0.0], [0.0, 0.0, 1.0, 0.0], [0.0, 0.0, 0.0, 1.0]], "instance_id": 0}, {"location": {"x": 1189.237, "y": 4882.468, "z": 464.122}, "transformation_": [[1.0, 0.0, 0.0, 0.0], [0.0, 1.0, 0.0, 0.0], [0.0, 0.0, 1.0, 0.0], [0.0, 0.0, 0.0, 1.0]], "instance_id": 0}, {"location": {"x": 1649.873, "y": 4985.285, "z": 473.544}, "transformation_": [[1.0, 0.0, 0.0, 0.0], [0.0, 1.0, 0.0, 0.0], [0.0, 0.0, 1.0, 0.0], [0.0, 0.0, 0.0, 1.0]], "instance_id": 0}, {"location": {"x": 2165.042, "y": 4617.759, "z": 846.807}, "transformation_": [[1.0, 0.0, 0.0, 0.0], [0.0, 1.0, 0.0, 0.0], [0.0, 0.0, 1.0, 0.0], [0.0, 0.0, 0.0, 1.0]], "instance_id": 0}, {"location": {"x": 2215.952, "y": 4694.502, "z": 928.61}, "transformation_": [[1.0, 0.0, 0.0, 0.0], [0.0, 1.0, 0.0, 0.0], [0.0, 0.0, 1.0, 0.0], [0.0, 0.0, 0.0, 1.0]], "instance_id": 0}, {"location": {"x": 2276.394, "y": 4608.261, "z": 802.558}, "transformation_": [[1.0, 0.0, 0.0, 0.0], [0.0, 1.0, 0.0, 0.0], [0.0, 0.0, 1.0, 0.0], [0.0, 0.0, 0.0, 1.0]], "instance_id": 0}, {"location": {"x": 2137.354, "y": 3437.938, "z": 600.0}, "transformation_": [[1.0, 0.0, 0.0, 0.0], [0.0, 1.0, 0.0, 0.0], [0.0, 0.0, 1.0, 0.0], [0.0, 0.0, 0.0, 1.0]], "instance_id": 0}, {"location": {"x": 1685.81, "y": 3815.229, "z": 1354.985}, "transformation_": [[1.0, 0.0, 0.0, 0.0], [0.0, 1.0, 0.0, 0.0], [0.0, 0.0, 1.0, 0.0], [0.0, 0.0, 0.0, 1.0]], "instance_id": 0}], "trust_orientation": true}